{"nodes": [{"id": "cluster_1", "group": "1", "label": "CLUSTER_1", "level": 27}, {"id": "cluster_2", "group": "2", "label": "CLUSTER_2", "level": 25}, {"id": "cluster_3", "group": "3", "label": "CLUSTER_3", "level": 28}, {"id": "cluster_4", "group": "4", "label": "CLUSTER_4", "level": 31}, {"id": "cluster_5", "group": "5", "label": "CLUSTER_5", "level": 19}, {"id": "cluster_6", "group": "6", "label": "CLUSTER_6", "level": 12}, {"id": "cluster_7", "group": "7", "label": "CLUSTER_7", "level": 22}, {"id": "cluster_8", "group": "8", "label": "CLUSTER_8", "level": 3}, {"id": "cluster_9", "group": "9", "label": "CLUSTER_9", "level": 5}, {"id": "cluster_10", "group": "10", "label": "CLUSTER_10", "level": 46}, {"id": "center", "group": "0", "label": "CENTER", "level": 1}], "links": [{"target": "cluster_1", "source": "cluster_2", "strength": 49.71424341251846}, {"target": "cluster_1", "source": "cluster_3", "strength": 49.807256622002946}, {"target": "cluster_1", "source": "cluster_4", "strength": 49.91132195526421}, {"target": "cluster_1", "source": "cluster_5", "strength": 49.8133942656545}, {"target": "cluster_1", "source": "cluster_6", "strength": 49.80352712189617}, {"target": "cluster_1", "source": "cluster_7", "strength": 49.55749236498337}, {"target": "cluster_1", "source": "cluster_8", "strength": 49.86694092880675}, {"target": "cluster_1", "source": "cluster_9", "strength": 49.90548150193744}, {"target": "cluster_1", "source": "cluster_10", "strength": 49.91930768396741}, {"target": "cluster_2", "source": "cluster_1", "strength": 49.71424341251846}, {"target": "cluster_2", "source": "cluster_3", "strength": 49.59497911350062}, {"target": "cluster_2", "source": "cluster_4", "strength": 49.681467936723244}, {"target": "cluster_2", "source": "cluster_5", "strength": 49.68533076407221}, {"target": "cluster_2", "source": "cluster_6", "strength": 49.84989413967172}, {"target": "cluster_2", "source": "cluster_7", "strength": 49.84324893244543}, {"target": "cluster_2", "source": "cluster_8", "strength": 49.84538968081053}, {"target": "cluster_2", "source": "cluster_9", "strength": 49.678134861636146}, {"target": "cluster_2", "source": "cluster_10", "strength": 49.746845527332226}, {"target": "cluster_3", "source": "cluster_1", "strength": 49.807256622002946}, {"target": "cluster_3", "source": "cluster_2", "strength": 49.59497911350062}, {"target": "cluster_3", "source": "cluster_4", "strength": 49.73167675097208}, {"target": "cluster_3", "source": "cluster_5", "strength": 49.88997974920374}, {"target": "cluster_3", "source": "cluster_6", "strength": 49.73768007564423}, {"target": "cluster_3", "source": "cluster_7", "strength": 49.44956650340203}, {"target": "cluster_3", "source": "cluster_8", "strength": 49.714414881632024}, {"target": "cluster_3", "source": "cluster_9", "strength": 49.898823123257685}, {"target": "cluster_3", "source": "cluster_10", "strength": 49.8383122561848}, {"target": "cluster_4", "source": "cluster_1", "strength": 49.91132195526421}, {"target": "cluster_4", "source": "cluster_2", "strength": 49.681467936723244}, {"target": "cluster_4", "source": "cluster_3", "strength": 49.73167675097208}, {"target": "cluster_4", "source": "cluster_5", "strength": 49.724878106476844}, {"target": "cluster_4", "source": "cluster_6", "strength": 49.73487988621554}, {"target": "cluster_4", "source": "cluster_7", "strength": 49.52863323272361}, {"target": "cluster_4", "source": "cluster_8", "strength": 49.831952028165055}, {"target": "cluster_4", "source": "cluster_9", "strength": 49.822071461558274}, {"target": "cluster_4", "source": "cluster_10", "strength": 49.832675548239834}, {"target": "cluster_5", "source": "cluster_1", "strength": 49.8133942656545}, {"target": "cluster_5", "source": "cluster_2", "strength": 49.68533076407221}, {"target": "cluster_5", "source": "cluster_3", "strength": 49.88997974920374}, {"target": "cluster_5", "source": "cluster_4", "strength": 49.724878106476844}, {"target": "cluster_5", "source": "cluster_6", "strength": 49.83461919090231}, {"target": "cluster_5", "source": "cluster_7", "strength": 49.54882599077199}, {"target": "cluster_5", "source": "cluster_8", "strength": 49.77519392195493}, {"target": "cluster_5", "source": "cluster_9", "strength": 49.893366935312976}, {"target": "cluster_5", "source": "cluster_10", "strength": 49.88414983274936}, {"target": "cluster_6", "source": "cluster_1", "strength": 49.80352712189617}, {"target": "cluster_6", "source": "cluster_2", "strength": 49.84989413967172}, {"target": "cluster_6", "source": "cluster_3", "strength": 49.73768007564423}, {"target": "cluster_6", "source": "cluster_4", "strength": 49.73487988621554}, {"target": "cluster_6", "source": "cluster_5", "strength": 49.83461919090231}, {"target": "cluster_6", "source": "cluster_7", "strength": 49.71179665028217}, {"target": "cluster_6", "source": "cluster_8", "strength": 49.880216163456815}, {"target": "cluster_6", "source": "cluster_9", "strength": 49.806180517815044}, {"target": "cluster_6", "source": "cluster_10", "strength": 49.86814497638367}, {"target": "cluster_7", "source": "cluster_1", "strength": 49.55749236498337}, {"target": "cluster_7", "source": "cluster_2", "strength": 49.84324893244543}, {"target": "cluster_7", "source": "cluster_3", "strength": 49.44956650340203}, {"target": "cluster_7", "source": "cluster_4", "strength": 49.52863323272361}, {"target": "cluster_7", "source": "cluster_5", "strength": 49.54882599077199}, {"target": "cluster_7", "source": "cluster_6", "strength": 49.71179665028217}, {"target": "cluster_7", "source": "cluster_8", "strength": 49.68907888724268}, {"target": "cluster_7", "source": "cluster_9", "strength": 49.52579541079495}, {"target": "cluster_7", "source": "cluster_10", "strength": 49.59377310758476}, {"target": "cluster_8", "source": "cluster_1", "strength": 49.86694092880675}, {"target": "cluster_8", "source": "cluster_2", "strength": 49.84538968081053}, {"target": "cluster_8", "source": "cluster_3", "strength": 49.714414881632024}, {"target": "cluster_8", "source": "cluster_4", "strength": 49.831952028165055}, {"target": "cluster_8", "source": "cluster_5", "strength": 49.77519392195493}, {"target": "cluster_8", "source": "cluster_6", "strength": 49.880216163456815}, {"target": "cluster_8", "source": "cluster_7", "strength": 49.68907888724268}, {"target": "cluster_8", "source": "cluster_9", "strength": 49.811114863388944}, {"target": "cluster_8", "source": "cluster_10", "strength": 49.876055132722485}, {"target": "cluster_9", "source": "cluster_1", "strength": 49.90548150193744}, {"target": "cluster_9", "source": "cluster_2", "strength": 49.678134861636146}, {"target": "cluster_9", "source": "cluster_3", "strength": 49.898823123257685}, {"target": "cluster_9", "source": "cluster_4", "strength": 49.822071461558274}, {"target": "cluster_9", "source": "cluster_5", "strength": 49.893366935312976}, {"target": "cluster_9", "source": "cluster_6", "strength": 49.806180517815044}, {"target": "cluster_9", "source": "cluster_7", "strength": 49.52579541079495}, {"target": "cluster_9", "source": "cluster_8", "strength": 49.811114863388944}, {"target": "cluster_9", "source": "cluster_10", "strength": 49.931177789924085}, {"target": "cluster_10", "source": "cluster_1", "strength": 49.91930768396741}, {"target": "cluster_10", "source": "cluster_2", "strength": 49.746845527332226}, {"target": "cluster_10", "source": "cluster_3", "strength": 49.8383122561848}, {"target": "cluster_10", "source": "cluster_4", "strength": 49.832675548239834}, {"target": "cluster_10", "source": "cluster_5", "strength": 49.88414983274936}, {"target": "cluster_10", "source": "cluster_6", "strength": 49.86814497638367}, {"target": "cluster_10", "source": "cluster_7", "strength": 49.59377310758476}, {"target": "cluster_10", "source": "cluster_8", "strength": 49.876055132722485}, {"target": "cluster_10", "source": "cluster_9", "strength": 49.931177789924085}]}
